haai/hello.py
haai-0.0.1.dist-info/METADATA
haai-0.0.1.dist-info/WHEEL
haai-0.0.1.dist-info/top_level.txt
haai-0.0.1.dist-info/RECORD
